nnx/__init__.py
nnx/containers.py
nnx/contextlib.py
nnx/dataclasses.py
nnx/errors.py
nnx/helpers.py
nnx/ids.py
nnx/module.py
nnx/nn/__init__.py
nnx/nn/activations.py
nnx/nn/dtypes.py
nnx/nn/initializers.py
nnx/nn/linear.py
nnx/nn/normalization.py
nnx/nn/stochastic.py
nnx/nodes.py
nnx/partitioning.py
nnx/pytreelib.py
nnx/reprlib.py
nnx/spmd.py
nnx/state.py
nnx/tracers.py
nnx/transforms.py
nnx-0.0.8.dist-info/LICENSE
nnx-0.0.8.dist-info/METADATA
nnx-0.0.8.dist-info/WHEEL
nnx-0.0.8.dist-info/RECORD
