Metadata-Version: 2.1
Name: nnx
Version: 0.0.8
Summary: 
Author: Cristian Garcia
Author-email: cgarcia.e88@gmail.com
Requires-Python: >=3.9,<3.12
Classifier: Programming Language :: Python :: 3
Classifier: Programming Language :: Python :: 3.9
Classifier: Programming Language :: Python :: 3.10
Classifier: Programming Language :: Python :: 3.11
Requires-Dist: jax
Requires-Dist: jaxlib
Requires-Dist: optax
Requires-Dist: typing-extensions
